{
  "origin": {
    "coordinate": [
      8,
      6
    ],
    "direction": "W"
  },
  "destinations": [
    [
      8,
      1
    ],
    [
      5,
      1
    ],
    [
      7,
      4
    ],
    [
      6,
      1
    ],
    [
      0,
      1
    ],
    [
      0,
      6
    ],
    [
      1,
      6
    ]
  ],
  "path": [
    {
      "coordinate": [
        8,
        6
      ],
      "connectedNodes": [
        1
      ]
    },
    {
      "coordinate": [
        7,
        6
      ],
      "connectedNodes": [
        2,
        0
      ]
    },
    {
      "coordinate": [
        6,
        6
      ],
      "connectedNodes": [
        1,
        3
      ]
    },
    {
      "coordinate": [
        6,
        5
      ],
      "connectedNodes": [
        2,
        4
      ]
    },
    {
      "coordinate": [
        7,
        5
      ],
      "connectedNodes": [
        3,
        5
      ]
    },
    {
      "coordinate": [
        7,
        4
      ],
      "connectedNodes": [
        6,
        4
      ]
    },
    {
      "coordinate": [
        6,
        4
      ],
      "connectedNodes": [
        7,
        5
      ]
    },
    {
      "coordinate": [
        5,
        4
      ],
      "connectedNodes": [
        8,
        6
      ]
    },
    {
      "coordinate": [
        5,
        5
      ],
      "connectedNodes": [
        9,
        7
      ]
    },
    {
      "coordinate": [
        5,
        6
      ],
      "connectedNodes": [
        10,
        8
      ]
    },
    {
      "coordinate": [
        4,
        6
      ],
      "connectedNodes": [
        11,
        9
      ]
    },
    {
      "coordinate": [
        3,
        6
      ],
      "connectedNodes": [
        12,
        10
      ]
    },
    {
      "coordinate": [
        2,
        6
      ],
      "connectedNodes": [
        11,
        13
      ]
    },
    {
      "coordinate": [
        2,
        5
      ],
      "connectedNodes": [
        12,
        14
      ]
    },
    {
      "coordinate": [
        3,
        5
      ],
      "connectedNodes": [
        13,
        15
      ]
    },
    {
      "coordinate": [
        3,
        4
      ],
      "connectedNodes": [
        16,
        14
      ]
    },
    {
      "coordinate": [
        2,
        4
      ],
      "connectedNodes": [
        17,
        15
      ]
    },
    {
      "coordinate": [
        1,
        4
      ],
      "connectedNodes": [
        18,
        16
      ]
    },
    {
      "coordinate": [
        1,
        5
      ],
      "connectedNodes": [
        19,
        17
      ]
    },
    {
      "coordinate": [
        1,
        6
      ],
      "connectedNodes": [
        20,
        18
      ]
    },
    {
      "coordinate": [
        0,
        6
      ],
      "connectedNodes": [
        19,
        21
      ]
    },
    {
      "coordinate": [
        0,
        5
      ],
      "connectedNodes": [
        20,
        22
      ]
    },
    {
      "coordinate": [
        0,
        4
      ],
      "connectedNodes": [
        21,
        23
      ]
    },
    {
      "coordinate": [
        0,
        3
      ],
      "connectedNodes": [
        22,
        24
      ]
    },
    {
      "coordinate": [
        0,
        2
      ],
      "connectedNodes": [
        23,
        25
      ]
    },
    {
      "coordinate": [
        0,
        1
      ],
      "connectedNodes": [
        24,
        26
      ]
    },
    {
      "coordinate": [
        1,
        1
      ],
      "connectedNodes": [
        25,
        27
      ]
    },
    {
      "coordinate": [
        2,
        1
      ],
      "connectedNodes": [
        26,
        28
      ]
    },
    {
      "coordinate": [
        3,
        1
      ],
      "connectedNodes": [
        27,
        29
      ]
    },
    {
      "coordinate": [
        4,
        1
      ],
      "connectedNodes": [
        28,
        30
      ]
    },
    {
      "coordinate": [
        5,
        1
      ],
      "connectedNodes": [
        29,
        33
      ]
    },
    {
      "coordinate": [
        6,
        3
      ],
      "connectedNodes": [
        32
      ]
    },
    {
      "coordinate": [
        6,
        2
      ],
      "connectedNodes": [
        31,
        33
      ]
    },
    {
      "coordinate": [
        6,
        1
      ],
      "connectedNodes": [
        30,
        32,
        34
      ]
    },
    {
      "coordinate": [
        7,
        1
      ],
      "connectedNodes": [
        33,
        35
      ]
    },
    {
      "coordinate": [
        8,
        1
      ],
      "connectedNodes": [
        34
      ]
    }
  ],
  "traffic_lights": "[]",
  "max_fuel": 50,
  "theme": "https://www.codeforlife.education/rapidrouter/api/themes/4/",
  "leveldecor_set": [
    {
      "url": "https://www.codeforlife.education/rapidrouter/api/leveldecors/8020/",
      "x": 682,
      "y": 228,
      "decorName": "tree1",
      "level": "https://www.codeforlife.education/rapidrouter/api/levels/611/"
    },
    {
      "url": "https://www.codeforlife.education/rapidrouter/api/leveldecors/8021/",
      "x": 186,
      "y": 189,
      "decorName": "pond",
      "level": "https://www.codeforlife.education/rapidrouter/api/levels/611/"
    },
    {
      "url": "https://www.codeforlife.education/rapidrouter/api/leveldecors/8022/",
      "x": 332,
      "y": 571,
      "decorName": "bush",
      "level": "https://www.codeforlife.education/rapidrouter/api/levels/611/"
    },
    {
      "url": "https://www.codeforlife.education/rapidrouter/api/leveldecors/8023/",
      "x": 404,
      "y": 506,
      "decorName": "tree2",
      "level": "https://www.codeforlife.education/rapidrouter/api/levels/611/"
    },
    {
      "url": "https://www.codeforlife.education/rapidrouter/api/leveldecors/8024/",
      "x": 98,
      "y": 191,
      "decorName": "bush",
      "level": "https://www.codeforlife.education/rapidrouter/api/levels/611/"
    },
    {
      "url": "https://www.codeforlife.education/rapidrouter/api/leveldecors/8025/",
      "x": 97,
      "y": 251,
      "decorName": "bush",
      "level": "https://www.codeforlife.education/rapidrouter/api/levels/611/"
    },
    {
      "url": "https://www.codeforlife.education/rapidrouter/api/leveldecors/8026/",
      "x": 98,
      "y": 315,
      "decorName": "bush",
      "level": "https://www.codeforlife.education/rapidrouter/api/levels/611/"
    },
    {
      "url": "https://www.codeforlife.education/rapidrouter/api/leveldecors/8027/",
      "x": 354,
      "y": 192,
      "decorName": "bush",
      "level": "https://www.codeforlife.education/rapidrouter/api/levels/611/"
    },
    {
      "url": "https://www.codeforlife.education/rapidrouter/api/leveldecors/8028/",
      "x": 354,
      "y": 252,
      "decorName": "bush",
      "level": "https://www.codeforlife.education/rapidrouter/api/levels/611/"
    },
    {
      "url": "https://www.codeforlife.education/rapidrouter/api/leveldecors/8029/",
      "x": 354,
      "y": 317,
      "decorName": "bush",
      "level": "https://www.codeforlife.education/rapidrouter/api/levels/611/"
    },
    {
      "url": "https://www.codeforlife.education/rapidrouter/api/leveldecors/8030/",
      "x": 676,
      "y": 698,
      "decorName": "bush",
      "level": "https://www.codeforlife.education/rapidrouter/api/levels/611/"
    },
    {
      "url": "https://www.codeforlife.education/rapidrouter/api/leveldecors/8031/",
      "x": 750,
      "y": 700,
      "decorName": "bush",
      "level": "https://www.codeforlife.education/rapidrouter/api/levels/611/"
    },
    {
      "url": "https://www.codeforlife.education/rapidrouter/api/leveldecors/8032/",
      "x": 297,
      "y": 357,
      "decorName": "bush",
      "level": "https://www.codeforlife.education/rapidrouter/api/levels/611/"
    },
    {
      "url": "https://www.codeforlife.education/rapidrouter/api/leveldecors/8033/",
      "x": 230,
      "y": 357,
      "decorName": "bush",
      "level": "https://www.codeforlife.education/rapidrouter/api/levels/611/"
    },
    {
      "url": "https://www.codeforlife.education/rapidrouter/api/leveldecors/8034/",
      "x": 160,
      "y": 356,
      "decorName": "bush",
      "level": "https://www.codeforlife.education/rapidrouter/api/levels/611/"
    },
    {
      "url": "https://www.codeforlife.education/rapidrouter/api/leveldecors/8035/",
      "x": 902,
      "y": 550,
      "decorName": "bush",
      "level": "https://www.codeforlife.education/rapidrouter/api/levels/611/"
    },
    {
      "url": "https://www.codeforlife.education/rapidrouter/api/leveldecors/8036/",
      "x": 827,
      "y": 550,
      "decorName": "bush",
      "level": "https://www.codeforlife.education/rapidrouter/api/levels/611/"
    },
    {
      "url": "https://www.codeforlife.education/rapidrouter/api/leveldecors/8037/",
      "x": 754,
      "y": 552,
      "decorName": "bush",
      "level": "https://www.codeforlife.education/rapidrouter/api/levels/611/"
    },
    {
      "url": "https://www.codeforlife.education/rapidrouter/api/leveldecors/8038/",
      "x": 901,
      "y": 697,
      "decorName": "bush",
      "level": "https://www.codeforlife.education/rapidrouter/api/levels/611/"
    },
    {
      "url": "https://www.codeforlife.education/rapidrouter/api/leveldecors/8039/",
      "x": 826,
      "y": 699,
      "decorName": "bush",
      "level": "https://www.codeforlife.education/rapidrouter/api/levels/611/"
    },
    {
      "url": "https://www.codeforlife.education/rapidrouter/api/leveldecors/8040/",
      "x": 904,
      "y": 627,
      "decorName": "bush",
      "level": "https://www.codeforlife.education/rapidrouter/api/levels/611/"
    }
  ]
}